cassiny/__init__.py
cassiny/__version__.py
cassiny/cli.py
cassiny/config.py
cassiny/utils.py
cassiny/apis/__init__.py
cassiny/apis/commands.py
cassiny/auth/__init__.py
cassiny/auth/commands.py
cassiny/blueprints/__init__.py
cassiny/blueprints/commands.py
cassiny/blueprints/utils.py
cassiny/cargos/__init__.py
cassiny/cargos/commands.py
cassiny/jobs/__init__.py
cassiny/jobs/commands.py
cassiny/logs/__init__.py
cassiny/logs/commands.py
cassiny/probes/__init__.py
cassiny/probes/commands.py
cassiny-0.0.7.dist-info/DESCRIPTION.rst
cassiny-0.0.7.dist-info/METADATA
cassiny-0.0.7.dist-info/RECORD
cassiny-0.0.7.dist-info/WHEEL
cassiny-0.0.7.dist-info/entry_points.txt
cassiny-0.0.7.dist-info/metadata.json
cassiny-0.0.7.dist-info/top_level.txt
