Metadata-Version: 2.0
Name: cassiny
Version: 0.0.7
Summary: A CLI to interact with Cassiny's services.
Home-page: https://github.com/cassinyio/cassiny-cli
Author: Christian Barra
Author-email: wow@cassiny.io
License: Apache
Platform: UNKNOWN
Classifier: License :: OSI Approved :: Apache Software License
Classifier: Programming Language :: Python
Classifier: Programming Language :: Python :: 3.6
Classifier: Programming Language :: Python :: 3.7
Classifier: Programming Language :: Python :: Implementation :: CPython
Requires-Dist: click
Requires-Dist: requests
Requires-Dist: requests-toolbelt
Requires-Dist: terminaltables
